git_version/__init__.py
git_version/apps.py
git_version/tests.py
git_version/templatetags/__init__.py
git_version/templatetags/git_tags.py
django_git_version-0.1.0.dist-info/METADATA
django_git_version-0.1.0.dist-info/WHEEL
django_git_version-0.1.0.dist-info/top_level.txt
django_git_version-0.1.0.dist-info/RECORD
