Metadata-Version: 2.1
Name: django-git-version
Version: 0.1.0
Summary: django 
Home-page: https://github.com/d120/django-git-version
Author: Daniel Seiler
Author-email: daniel.seiler@fachschaft.informatik.tu-darmstadt.de
License: MIT
Platform: UNKNOWN
Classifier: Environment :: Web Environment
Classifier: Framework :: Django
Classifier: Operating System :: OS Independent
Classifier: Programming Language :: Python
Classifier: Programming Language :: Python :: 3
Requires-Dist: django (<4)
Requires-Dist: gitpython
